overseer_framework/__init__.py
overseer_framework/cli.py
overseer_framework-0.1.1.dist-info/entry_points.txt
overseer_framework-0.1.1.dist-info/WHEEL
overseer_framework-0.1.1.dist-info/METADATA
overseer_framework-0.1.1.dist-info/RECORD
